MANIFEST.in
README
README.md
setup.py
foxylib/__init__.py
foxylib/version.py
foxylib.egg-info/PKG-INFO
foxylib.egg-info/SOURCES.txt
foxylib.egg-info/dependency_links.txt
foxylib.egg-info/requires.txt
foxylib.egg-info/top_level.txt
foxylib/tools/__init__.py
foxylib/tools/arithmetic/__init__.py
foxylib/tools/arithmetic/arithmetic_tool.py
foxylib/tools/async/__init__.py
foxylib/tools/async/async_tool.py
foxylib/tools/async/tests/__init__.py
foxylib/tools/async/tests/sample.py
foxylib/tools/async/tests/test_async_tool.py
foxylib/tools/auth/__init__.py
foxylib/tools/auth/auth0/__init__.py
foxylib/tools/auth/auth0/auth0_tool.py
foxylib/tools/auth/auth0/foxylib_auth0.py
foxylib/tools/auth/auth0/tests/__init__.py
foxylib/tools/auth/auth0/tests/test_foxylib_auth0.py
foxylib/tools/aws/__init__.py
foxylib/tools/aws/aws_tool.py
foxylib/tools/binary2text/__init__.py
foxylib/tools/binary2text/base64_tool.py
foxylib/tools/bytes/__init__.py
foxylib/tools/bytes/bytes_tool.py
foxylib/tools/bytes/tests/__init__.py
foxylib/tools/bytes/tests/test_bytes_tool.py
foxylib/tools/cache/__init__.py
foxylib/tools/cache/cache_tool.py
foxylib/tools/collections/__init__.py
foxylib/tools/collections/chunk_tool.py
foxylib/tools/collections/collections_tool.py
foxylib/tools/collections/groupby_tool.py
foxylib/tools/collections/index_tool.py
foxylib/tools/collections/sort_tool.py
foxylib/tools/collections/tests/__init__.py
foxylib/tools/collections/tests/test_chunk_tools.py
foxylib/tools/collections/tests/test_collections_tools.py
foxylib/tools/collections/tests/test_iter_tool.py
foxylib/tools/compare/__init__.py
foxylib/tools/compare/compare_tool.py
foxylib/tools/compare/minimax_tool.py
foxylib/tools/csv/__init__.py
foxylib/tools/csv/csv_tool.py
foxylib/tools/data_visualization/__init__.py
foxylib/tools/data_visualization/flourish/__init__.py
foxylib/tools/data_visualization/flourish/flourish_tool.py
foxylib/tools/database/__init__.py
foxylib/tools/database/elasticsearch/__init__.py
foxylib/tools/database/elasticsearch/elasticsearch_tool.py
foxylib/tools/database/mongodb/__init__.py
foxylib/tools/database/mongodb/document_migration_tool.py
